terminalpoint/__init__.py
terminalpoint/__main__.py
terminalpoint/_version.py
terminalpoint/app.py
terminalpoint/py.typed
terminalpoint-0.2.0.dist-info/LICENSE
terminalpoint-0.2.0.dist-info/METADATA
terminalpoint-0.2.0.dist-info/WHEEL
terminalpoint-0.2.0.dist-info/entry_points.txt
terminalpoint-0.2.0.dist-info/top_level.txt
terminalpoint-0.2.0.dist-info/RECORD
