Metadata-Version: 2.1
Name: terminalpoint
Version: 0.2.0
Summary: TerminalPoint let's you do your presentations in the Terminal
Home-page: https://github.com/ap--/terminalpoint
Maintainer-email: andreas@poehlmann.io
License: MIT
Platform: any
Classifier: Programming Language :: Python :: 3
Classifier: Programming Language :: Python :: 3.8
Classifier: Programming Language :: Python :: 3.9
Classifier: Programming Language :: Python :: 3.10
Classifier: Programming Language :: Python :: 3.11
Classifier: Programming Language :: Python :: 3.12
Classifier: Development Status :: 3 - Alpha
Requires-Python: >=3.8
License-File: LICENSE
Requires-Dist: textual >=0.53.0
Requires-Dist: typer >=0.9.0
Requires-Dist: typing-extensions ; python_version < "3.9"
Provides-Extra: dev
Requires-Dist: build ; extra == 'dev'
Requires-Dist: twine ; extra == 'dev'
Requires-Dist: wheel ; extra == 'dev'
